sphinx_rigado_extensions/__init__.py
sphinx_rigado_extensions/inventory-builder.py
sphinx_rigado_extensions/tablelist.py
sphinx_rigado_extensions-0.0.2.dist-info/METADATA
sphinx_rigado_extensions-0.0.2.dist-info/RECORD
sphinx_rigado_extensions-0.0.2.dist-info/WHEEL
sphinx_rigado_extensions-0.0.2.dist-info/top_level.txt
sphinxcontrib/rigado/__init__.py
sphinxcontrib/rigado/inventory-builder.py
sphinxcontrib/rigado/tablelist.py
