Metadata-Version: 2.1
Name: sphinx-rigado-extensions
Version: 0.0.2
Summary: Sphinx extensions for Rigado
Home-page: https://git.rigado.com/documentation/sphinx
Author: Spencer Williams
Author-email: spencer.williams@rigado.com
License: MIT
Platform: UNKNOWN
